{"round": 14, "history": [{"x": 51, "y": 50}, {"x": 52, "y": 51}, {"x": 54, "y": 51}, {"x": 55, "y": 52}, {"x": 56, "y": 53}, {"x": 57, "y": 54}, {"x": 59, "y": 54}, {"x": 60, "y": 55}, {"x": 61, "y": 56}, {"x": 63, "y": 57}, {"x": 64, "y": 58}, {"x": 65, "y": 58}, {"x": 66, "y": 59}, {"x": 67, "y": 61}, {"x": 68, "y": 62}, {"x": 69, "y": 63}, {"x": 70, "y": 64}, {"x": 71, "y": 65}, {"x": 72, "y": 66}, {"x": 73, "y": 67}, {"x": 74, "y": 68}, {"x": 75, "y": 69}, {"x": 76, "y": 71}, {"x": 77, "y": 72}, {"x": 78, "y": 73}, {"x": 79, "y": 74}, {"x": 79, "y": 75}, {"x": 80, "y": 77}, {"x": 81, "y": 78}, {"x": 82, "y": 79}, {"x": 83, "y": 80}, {"x": 84, "y": 81}, {"x": 85, "y": 82}, {"x": 86, "y": 83}, {"x": 87, "y": 85}, {"x": 88, "y": 86}, {"x": 89, "y": 87}, {"x": 91, "y": 87}, {"x": 92, "y": 88}, {"x": 93, "y": 89}, {"x": 94, "y": 91}, {"x": 95, "y": 92}, {"x": 96, "y": 93}, {"x": 97, "y": 94}, {"x": 98, "y": 95}, {"x": 99, "y": 96}, {"x": 101, "y": 97}, {"x": 102, "y": 98}, {"x": 103, "y": 99}, {"x": 104, "y": 100}, {"x": 105, "y": 101}, {"x": 106, "y": 101}, {"x": 107, "y": 102}, {"x": 109, "y": 103}, {"x": 110, "y": 104}, {"x": 111, "y": 105}, {"x": 112, "y": 107}, {"x": 113, "y": 108}, {"x": 114, "y": 109}, {"x": 115, "y": 110}, {"x": 115, "y": 111}, {"x": 116, "y": 113}, {"x": 116, "y": 114}, {"x": 116, "y": 116}, {"x": 116, "y": 117}, {"x": 117, "y": 119}, {"x": 117, "y": 120}, {"x": 117, "y": 122}, {"x": 118, "y": 123}, {"x": 118, "y": 125}, {"x": 119, "y": 126}, {"x": 119, "y": 127}, {"x": 120, "y": 129}, {"x": 120, "y": 130}, {"x": 120, "y": 132}, {"x": 121, "y": 133}, {"x": 121, "y": 135}, {"x": 121, "y": 136}, {"x": 121, "y": 138}, {"x": 122, "y": 139}, {"x": 122, "y": 141}, {"x": 122, "y": 142}, {"x": 122, "y": 144}, {"x": 123, "y": 145}, {"x": 123, "y": 147}, {"x": 123, "y": 148}, {"x": 123, "y": 150}, {"x": 123, "y": 151}, {"x": 123, "y": 153}, {"x": 123, "y": 154}, {"x": 123, "y": 155}, {"x": 124, "y": 157}, {"x": 124, "y": 158}, {"x": 124, "y": 160}, {"x": 124, "y": 161}, {"x": 125, "y": 163}, {"x": 125, "y": 164}, {"x": 125, "y": 166}, {"x": 125, "y": 167}, {"x": 125, "y": 169}, {"x": 125, "y": 170}, {"x": 126, "y": 172}, {"x": 126, "y": 173}, {"x": 126, "y": 175}, {"x": 127, "y": 176}, {"x": 127, "y": 178}, {"x": 127, "y": 179}, {"x": 127, "y": 181}, {"x": 127, "y": 182}, {"x": 127, "y": 184}, {"x": 127, "y": 185}, {"x": 127, "y": 187}, {"x": 127, "y": 188}, {"x": 127, "y": 190}, {"x": 127, "y": 191}, {"x": 126, "y": 193}, {"x": 125, "y": 194}, {"x": 125, "y": 195}, {"x": 124, "y": 196}, {"x": 123, "y": 197}, {"x": 121, "y": 198}, {"x": 120, "y": 199}, {"x": 119, "y": 200}, {"x": 117, "y": 200}, {"x": 116, "y": 201}, {"x": 115, "y": 201}, {"x": 113, "y": 201}, {"x": 112, "y": 201}, {"x": 110, "y": 201}, {"x": 109, "y": 200}, {"x": 107, "y": 200}, {"x": 106, "y": 199}, {"x": 104, "y": 199}, {"x": 103, "y": 198}, {"x": 102, "y": 197}, {"x": 101, "y": 196}, {"x": 101, "y": 194}, {"x": 100, "y": 193}, {"x": 100, "y": 191}, {"x": 99, "y": 190}, {"x": 99, "y": 188}, {"x": 99, "y": 187}, {"x": 99, "y": 185}, {"x": 99, "y": 184}, {"x": 99, "y": 182}, {"x": 100, "y": 181}, {"x": 100, "y": 180}, {"x": 101, "y": 178}, {"x": 102, "y": 177}, {"x": 103, "y": 176}, {"x": 103, "y": 174}, {"x": 104, "y": 173}, {"x": 106, "y": 172}, {"x": 107, "y": 172}, {"x": 108, "y": 171}, {"x": 110, "y": 171}, {"x": 111, "y": 170}, {"x": 113, "y": 170}, {"x": 114, "y": 170}, {"x": 116, "y": 170}], "timestamp": 13.795713424682617, "best_score": 771}