{"round": 31, "history": [{"x": 46, "y": 45}, {"x": 45, "y": 44}, {"x": 45, "y": 42}, {"x": 44, "y": 41}, {"x": 44, "y": 39}, {"x": 44, "y": 38}, {"x": 43, "y": 36}, {"x": 43, "y": 35}, {"x": 44, "y": 33}, {"x": 44, "y": 32}, {"x": 45, "y": 31}, {"x": 45, "y": 29}, {"x": 46, "y": 28}, {"x": 47, "y": 27}, {"x": 48, "y": 26}, {"x": 49, "y": 25}, {"x": 50, "y": 24}, {"x": 51, "y": 23}, {"x": 52, "y": 22}, {"x": 54, "y": 21}, {"x": 55, "y": 20}, {"x": 56, "y": 19}, {"x": 57, "y": 17}, {"x": 58, "y": 16}, {"x": 59, "y": 15}, {"x": 60, "y": 14}, {"x": 61, "y": 14}, {"x": 63, "y": 13}, {"x": 64, "y": 12}, {"x": 65, "y": 12}, {"x": 67, "y": 11}, {"x": 68, "y": 11}, {"x": 70, "y": 11}, {"x": 71, "y": 11}, {"x": 73, "y": 11}, {"x": 74, "y": 11}, {"x": 76, "y": 12}, {"x": 77, "y": 12}, {"x": 78, "y": 13}, {"x": 80, "y": 14}, {"x": 81, "y": 14}, {"x": 82, "y": 15}, {"x": 84, "y": 16}, {"x": 85, "y": 17}, {"x": 86, "y": 18}, {"x": 87, "y": 18}, {"x": 89, "y": 19}, {"x": 90, "y": 20}, {"x": 91, "y": 21}, {"x": 93, "y": 21}, {"x": 94, "y": 22}, {"x": 95, "y": 22}, {"x": 97, "y": 23}, {"x": 98, "y": 23}, {"x": 100, "y": 23}, {"x": 101, "y": 23}, {"x": 103, "y": 23}, {"x": 104, "y": 23}, {"x": 106, "y": 24}, {"x": 107, "y": 24}, {"x": 109, "y": 24}, {"x": 110, "y": 24}, {"x": 112, "y": 24}, {"x": 113, "y": 24}, {"x": 115, "y": 23}, {"x": 116, "y": 23}, {"x": 118, "y": 23}, {"x": 119, "y": 23}, {"x": 121, "y": 23}, {"x": 122, "y": 23}, {"x": 123, "y": 24}, {"x": 125, "y": 24}, {"x": 126, "y": 25}, {"x": 127, "y": 26}, {"x": 128, "y": 27}, {"x": 129, "y": 29}, {"x": 130, "y": 30}, {"x": 130, "y": 31}, {"x": 130, "y": 33}, {"x": 130, "y": 34}, {"x": 131, "y": 36}, {"x": 131, "y": 37}, {"x": 131, "y": 39}, {"x": 130, "y": 40}, {"x": 130, "y": 42}, {"x": 129, "y": 43}, {"x": 129, "y": 45}, {"x": 129, "y": 46}, {"x": 128, "y": 47}, {"x": 128, "y": 49}, {"x": 128, "y": 50}, {"x": 128, "y": 52}, {"x": 127, "y": 53}, {"x": 127, "y": 55}, {"x": 126, "y": 56}, {"x": 126, "y": 57}, {"x": 125, "y": 59}, {"x": 124, "y": 60}, {"x": 124, "y": 62}, {"x": 123, "y": 63}, {"x": 122, "y": 64}, {"x": 121, "y": 65}, {"x": 120, "y": 66}, {"x": 119, "y": 67}, {"x": 118, "y": 68}, {"x": 117, "y": 69}, {"x": 115, "y": 70}, {"x": 114, "y": 71}, {"x": 113, "y": 72}, {"x": 112, "y": 73}, {"x": 110, "y": 73}, {"x": 109, "y": 74}, {"x": 108, "y": 75}, {"x": 107, "y": 76}, {"x": 105, "y": 76}, {"x": 104, "y": 77}, {"x": 102, "y": 77}, {"x": 101, "y": 78}, {"x": 100, "y": 78}, {"x": 98, "y": 79}, {"x": 97, "y": 79}, {"x": 95, "y": 79}, {"x": 94, "y": 79}, {"x": 92, "y": 79}, {"x": 91, "y": 79}, {"x": 89, "y": 79}, {"x": 88, "y": 79}, {"x": 86, "y": 79}, {"x": 85, "y": 78}, {"x": 83, "y": 78}, {"x": 82, "y": 78}, {"x": 80, "y": 78}, {"x": 79, "y": 78}, {"x": 77, "y": 78}, {"x": 76, "y": 78}, {"x": 74, "y": 78}, {"x": 73, "y": 78}, {"x": 71, "y": 78}, {"x": 70, "y": 77}, {"x": 68, "y": 77}, {"x": 67, "y": 77}, {"x": 65, "y": 76}, {"x": 64, "y": 76}, {"x": 62, "y": 76}, {"x": 61, "y": 76}, {"x": 59, "y": 76}, {"x": 58, "y": 76}, {"x": 56, "y": 76}, {"x": 55, "y": 77}, {"x": 53, "y": 77}, {"x": 52, "y": 77}, {"x": 50, "y": 77}, {"x": 49, "y": 77}, {"x": 47, "y": 77}, {"x": 46, "y": 78}, {"x": 44, "y": 78}, {"x": 43, "y": 78}, {"x": 42, "y": 78}, {"x": 40, "y": 78}, {"x": 39, "y": 78}, {"x": 37, "y": 78}, {"x": 36, "y": 78}, {"x": 34, "y": 78}, {"x": 33, "y": 79}, {"x": 31, "y": 79}, {"x": 30, "y": 79}, {"x": 28, "y": 80}, {"x": 27, "y": 80}, {"x": 25, "y": 80}, {"x": 24, "y": 81}, {"x": 22, "y": 81}, {"x": 21, "y": 81}, {"x": 19, "y": 81}, {"x": 18, "y": 81}, {"x": 16, "y": 81}, {"x": 15, "y": 82}, {"x": 13, "y": 82}, {"x": 12, "y": 82}, {"x": 10, "y": 83}, {"x": 9, "y": 83}, {"x": 7, "y": 83}, {"x": 6, "y": 84}, {"x": 5, "y": 84}, {"x": 3, "y": 85}, {"x": 2, "y": 85}, {"x": 0, "y": 86}, {"x": 640, "y": 86}, {"x": 638, "y": 87}, {"x": 637, "y": 87}, {"x": 635, "y": 87}, {"x": 634, "y": 87}, {"x": 632, "y": 87}, {"x": 631, "y": 87}, {"x": 629, "y": 88}, {"x": 628, "y": 88}, {"x": 626, "y": 89}, {"x": 625, "y": 90}, {"x": 624, "y": 90}, {"x": 622, "y": 91}, {"x": 621, "y": 92}, {"x": 620, "y": 92}, {"x": 618, "y": 93}, {"x": 617, "y": 94}, {"x": 616, "y": 94}, {"x": 614, "y": 95}, {"x": 613, "y": 96}, {"x": 612, "y": 96}, {"x": 610, "y": 96}, {"x": 609, "y": 97}, {"x": 607, "y": 97}, {"x": 606, "y": 97}, {"x": 604, "y": 98}, {"x": 603, "y": 98}, {"x": 601, "y": 98}, {"x": 600, "y": 99}, {"x": 598, "y": 99}, {"x": 597, "y": 99}, {"x": 596, "y": 100}, {"x": 594, "y": 100}, {"x": 593, "y": 100}, {"x": 591, "y": 101}, {"x": 590, "y": 101}, {"x": 588, "y": 101}, {"x": 587, "y": 102}, {"x": 585, "y": 102}, {"x": 584, "y": 102}, {"x": 582, "y": 102}, {"x": 581, "y": 102}, {"x": 579, "y": 102}, {"x": 578, "y": 103}, {"x": 576, "y": 103}, {"x": 575, "y": 103}, {"x": 573, "y": 104}, {"x": 572, "y": 104}, {"x": 571, "y": 105}, {"x": 569, "y": 105}, {"x": 568, "y": 106}, {"x": 566, "y": 106}, {"x": 565, "y": 107}, {"x": 564, "y": 107}, {"x": 562, "y": 108}, {"x": 561, "y": 109}, {"x": 560, "y": 110}, {"x": 559, "y": 111}, {"x": 557, "y": 112}, {"x": 556, "y": 112}, {"x": 555, "y": 113}, {"x": 554, "y": 115}, {"x": 553, "y": 116}, {"x": 552, "y": 117}, {"x": 551, "y": 118}, {"x": 550, "y": 119}, {"x": 549, "y": 120}, {"x": 549, "y": 122}, {"x": 548, "y": 123}, {"x": 547, "y": 124}, {"x": 546, "y": 126}, {"x": 546, "y": 127}, {"x": 545, "y": 128}, {"x": 545, "y": 130}, {"x": 544, "y": 131}, {"x": 543, "y": 132}, {"x": 543, "y": 134}, {"x": 542, "y": 135}, {"x": 541, "y": 136}, {"x": 541, "y": 138}, {"x": 540, "y": 139}, {"x": 540, "y": 141}, {"x": 540, "y": 142}, {"x": 539, "y": 144}, {"x": 539, "y": 145}, {"x": 538, "y": 146}, {"x": 538, "y": 148}, {"x": 537, "y": 149}, {"x": 537, "y": 151}, {"x": 536, "y": 152}, {"x": 535, "y": 153}, {"x": 535, "y": 155}, {"x": 534, "y": 156}, {"x": 533, "y": 157}, {"x": 532, "y": 159}, {"x": 532, "y": 160}, {"x": 530, "y": 161}, {"x": 529, "y": 162}, {"x": 528, "y": 163}, {"x": 527, "y": 164}, {"x": 526, "y": 165}, {"x": 525, "y": 166}, {"x": 524, "y": 167}, {"x": 523, "y": 168}, {"x": 522, "y": 170}, {"x": 522, "y": 171}, {"x": 521, "y": 172}, {"x": 520, "y": 173}, {"x": 519, "y": 175}, {"x": 519, "y": 176}, {"x": 518, "y": 178}, {"x": 518, "y": 179}, {"x": 517, "y": 180}, {"x": 517, "y": 182}, {"x": 516, "y": 183}, {"x": 516, "y": 185}, {"x": 515, "y": 186}, {"x": 514, "y": 187}, {"x": 514, "y": 189}, {"x": 513, "y": 190}, {"x": 513, "y": 192}, {"x": 512, "y": 193}, {"x": 511, "y": 194}, {"x": 510, "y": 195}, {"x": 510, "y": 197}, {"x": 508, "y": 198}, {"x": 507, "y": 199}, {"x": 506, "y": 200}, {"x": 505, "y": 200}, {"x": 504, "y": 201}, {"x": 502, "y": 202}, {"x": 501, "y": 203}, {"x": 500, "y": 204}, {"x": 499, "y": 205}, {"x": 498, "y": 206}, {"x": 496, "y": 206}, {"x": 495, "y": 207}, {"x": 494, "y": 208}, {"x": 493, "y": 209}, {"x": 492, "y": 210}, {"x": 490, "y": 211}, {"x": 490, "y": 212}, {"x": 488, "y": 213}, {"x": 488, "y": 214}, {"x": 487, "y": 216}, {"x": 486, "y": 217}, {"x": 485, "y": 218}, {"x": 485, "y": 220}, {"x": 484, "y": 221}, {"x": 483, "y": 222}, {"x": 482, "y": 224}, {"x": 481, "y": 225}, {"x": 480, "y": 226}, {"x": 479, "y": 227}, {"x": 478, "y": 228}, {"x": 478, "y": 229}, {"x": 477, "y": 231}, {"x": 476, "y": 232}, {"x": 475, "y": 233}, {"x": 474, "y": 234}, {"x": 473, "y": 235}, {"x": 472, "y": 236}, {"x": 471, "y": 237}, {"x": 469, "y": 238}, {"x": 468, "y": 239}, {"x": 467, "y": 240}, {"x": 466, "y": 241}, {"x": 465, "y": 242}, {"x": 464, "y": 243}, {"x": 462, "y": 243}, {"x": 461, "y": 244}, {"x": 460, "y": 245}, {"x": 458, "y": 246}, {"x": 457, "y": 247}, {"x": 456, "y": 248}, {"x": 455, "y": 249}, {"x": 454, "y": 250}, {"x": 454, "y": 251}, {"x": 453, "y": 252}, {"x": 452, "y": 254}, {"x": 451, "y": 255}, {"x": 450, "y": 256}, {"x": 449, "y": 257}, {"x": 448, "y": 258}, {"x": 447, "y": 259}, {"x": 446, "y": 261}, {"x": 445, "y": 262}, {"x": 444, "y": 263}, {"x": 443, "y": 264}, {"x": 443, "y": 265}, {"x": 442, "y": 267}, {"x": 441, "y": 268}, {"x": 440, "y": 269}, {"x": 439, "y": 270}, {"x": 438, "y": 272}, {"x": 438, "y": 273}, {"x": 437, "y": 274}, {"x": 436, "y": 276}, {"x": 435, "y": 277}, {"x": 434, "y": 278}, {"x": 433, "y": 279}, {"x": 433, "y": 280}, {"x": 432, "y": 282}, {"x": 431, "y": 283}, {"x": 431, "y": 284}, {"x": 430, "y": 286}, {"x": 430, "y": 287}, {"x": 430, "y": 289}, {"x": 430, "y": 290}, {"x": 430, "y": 292}, {"x": 430, "y": 293}, {"x": 431, "y": 295}, {"x": 432, "y": 296}, {"x": 432, "y": 297}, {"x": 433, "y": 299}, {"x": 434, "y": 300}, {"x": 435, "y": 301}, {"x": 436, "y": 302}, {"x": 437, "y": 303}, {"x": 439, "y": 303}, {"x": 440, "y": 304}, {"x": 441, "y": 305}, {"x": 442, "y": 306}, {"x": 444, "y": 307}, {"x": 445, "y": 308}, {"x": 446, "y": 308}, {"x": 448, "y": 309}, {"x": 449, "y": 310}, {"x": 450, "y": 310}, {"x": 452, "y": 311}, {"x": 453, "y": 311}, {"x": 455, "y": 311}, {"x": 456, "y": 312}, {"x": 458, "y": 312}, {"x": 459, "y": 312}, {"x": 461, "y": 312}, {"x": 462, "y": 313}, {"x": 463, "y": 313}, {"x": 465, "y": 313}, {"x": 466, "y": 314}, {"x": 468, "y": 314}, {"x": 469, "y": 314}, {"x": 471, "y": 314}, {"x": 472, "y": 314}, {"x": 474, "y": 314}, {"x": 475, "y": 314}, {"x": 477, "y": 314}, {"x": 478, "y": 314}, {"x": 480, "y": 314}, {"x": 481, "y": 313}, {"x": 483, "y": 313}, {"x": 484, "y": 313}, {"x": 486, "y": 313}, {"x": 487, "y": 313}, {"x": 489, "y": 313}, {"x": 490, "y": 313}, {"x": 492, "y": 314}, {"x": 493, "y": 314}, {"x": 495, "y": 315}, {"x": 496, "y": 315}, {"x": 498, "y": 315}, {"x": 499, "y": 315}, {"x": 501, "y": 315}, {"x": 502, "y": 316}, {"x": 504, "y": 316}, {"x": 505, "y": 316}, {"x": 507, "y": 316}, {"x": 508, "y": 316}, {"x": 510, "y": 316}, {"x": 511, "y": 315}, {"x": 512, "y": 315}, {"x": 514, "y": 315}, {"x": 515, "y": 315}, {"x": 517, "y": 315}, {"x": 518, "y": 315}, {"x": 520, "y": 316}, {"x": 521, "y": 316}, {"x": 523, "y": 316}, {"x": 524, "y": 316}, {"x": 526, "y": 316}, {"x": 527, "y": 317}, {"x": 529, "y": 317}, {"x": 530, "y": 317}, {"x": 532, "y": 318}, {"x": 533, "y": 319}, {"x": 534, "y": 319}, {"x": 536, "y": 320}, {"x": 537, "y": 321}, {"x": 538, "y": 321}, {"x": 540, "y": 322}, {"x": 541, "y": 322}, {"x": 543, "y": 323}, {"x": 544, "y": 323}, {"x": 545, "y": 324}, {"x": 547, "y": 325}, {"x": 548, "y": 325}, {"x": 549, "y": 326}, {"x": 551, "y": 327}, {"x": 552, "y": 327}, {"x": 553, "y": 328}, {"x": 555, "y": 329}, {"x": 556, "y": 330}, {"x": 557, "y": 330}, {"x": 558, "y": 331}, {"x": 560, "y": 332}, {"x": 561, "y": 333}, {"x": 562, "y": 334}, {"x": 564, "y": 334}, {"x": 565, "y": 335}, {"x": 567, "y": 335}, {"x": 568, "y": 335}, {"x": 569, "y": 336}, {"x": 571, "y": 336}, {"x": 572, "y": 337}, {"x": 574, "y": 337}, {"x": 575, "y": 337}, {"x": 577, "y": 338}, {"x": 578, "y": 339}, {"x": 579, "y": 339}, {"x": 581, "y": 339}, {"x": 582, "y": 340}, {"x": 584, "y": 340}, {"x": 585, "y": 341}, {"x": 587, "y": 341}, {"x": 588, "y": 342}, {"x": 589, "y": 342}, {"x": 591, "y": 342}, {"x": 592, "y": 343}, {"x": 594, "y": 343}, {"x": 595, "y": 344}, {"x": 597, "y": 344}, {"x": 598, "y": 345}, {"x": 599, "y": 345}, {"x": 601, "y": 346}, {"x": 602, "y": 347}, {"x": 603, "y": 348}, {"x": 604, "y": 349}, {"x": 606, "y": 349}, {"x": 607, "y": 350}, {"x": 608, "y": 351}, {"x": 610, "y": 351}, {"x": 611, "y": 352}, {"x": 612, "y": 353}, {"x": 614, "y": 353}, {"x": 615, "y": 354}, {"x": 617, "y": 354}, {"x": 618, "y": 355}, {"x": 619, "y": 355}, {"x": 621, "y": 356}, {"x": 622, "y": 356}, {"x": 624, "y": 357}, {"x": 625, "y": 357}, {"x": 626, "y": 358}, {"x": 628, "y": 359}, {"x": 629, "y": 360}, {"x": 630, "y": 360}, {"x": 632, "y": 361}, {"x": 633, "y": 362}, {"x": 634, "y": 362}, {"x": 636, "y": 363}, {"x": 637, "y": 363}, {"x": 638, "y": 364}, {"x": 0, "y": 365}, {"x": 1, "y": 365}, {"x": 2, "y": 366}, {"x": 4, "y": 367}, {"x": 5, "y": 367}, {"x": 6, "y": 368}, {"x": 8, "y": 368}, {"x": 9, "y": 369}, {"x": 10, "y": 369}, {"x": 12, "y": 370}, {"x": 13, "y": 371}, {"x": 15, "y": 371}, {"x": 16, "y": 372}, {"x": 18, "y": 372}, {"x": 19, "y": 372}, {"x": 20, "y": 373}, {"x": 22, "y": 373}, {"x": 23, "y": 374}, {"x": 25, "y": 374}, {"x": 26, "y": 375}, {"x": 28, "y": 375}, {"x": 29, "y": 375}, {"x": 31, "y": 375}, {"x": 32, "y": 375}, {"x": 33, "y": 375}, {"x": 35, "y": 376}, {"x": 36, "y": 376}, {"x": 38, "y": 377}, {"x": 39, "y": 377}, {"x": 40, "y": 378}, {"x": 42, "y": 379}, {"x": 43, "y": 380}, {"x": 44, "y": 380}, {"x": 45, "y": 381}, {"x": 46, "y": 383}, {"x": 47, "y": 384}, {"x": 48, "y": 385}, {"x": 49, "y": 386}, {"x": 49, "y": 388}, {"x": 50, "y": 389}, {"x": 50, "y": 391}, {"x": 50, "y": 392}, {"x": 50, "y": 394}, {"x": 50, "y": 395}, {"x": 50, "y": 397}, {"x": 50, "y": 398}, {"x": 49, "y": 399}, {"x": 48, "y": 401}, {"x": 47, "y": 402}, {"x": 46, "y": 403}, {"x": 45, "y": 404}, {"x": 44, "y": 405}, {"x": 42, "y": 405}, {"x": 41, "y": 405}, {"x": 39, "y": 406}, {"x": 38, "y": 405}, {"x": 36, "y": 405}, {"x": 35, "y": 405}, {"x": 33, "y": 405}, {"x": 32, "y": 405}, {"x": 30, "y": 406}, {"x": 29, "y": 406}, {"x": 27, "y": 406}, {"x": 26, "y": 406}, {"x": 25, "y": 406}, {"x": 23, "y": 405}, {"x": 22, "y": 405}, {"x": 20, "y": 405}, {"x": 19, "y": 404}, {"x": 17, "y": 404}, {"x": 16, "y": 403}, {"x": 15, "y": 402}, {"x": 14, "y": 401}, {"x": 13, "y": 400}, {"x": 12, "y": 399}, {"x": 11, "y": 398}, {"x": 10, "y": 397}, {"x": 9, "y": 395}, {"x": 8, "y": 394}, {"x": 7, "y": 393}, {"x": 6, "y": 392}, {"x": 5, "y": 391}, {"x": 4, "y": 389}, {"x": 4, "y": 388}, {"x": 3, "y": 387}, {"x": 3, "y": 385}, {"x": 2, "y": 384}, {"x": 2, "y": 382}, {"x": 2, "y": 381}, {"x": 2, "y": 379}, {"x": 3, "y": 378}, {"x": 3, "y": 376}], "timestamp": 82.91913533210754, "best_score": 771}